noise_detector.py
noise_detector-1.1.0.dist-info/LICENSE
noise_detector-1.1.0.dist-info/METADATA
noise_detector-1.1.0.dist-info/WHEEL
noise_detector-1.1.0.dist-info/entry_points.txt
noise_detector-1.1.0.dist-info/top_level.txt
noise_detector-1.1.0.dist-info/RECORD
